openraft-2.0.3.dist-info/licenses/LICENSE
openraft-2.0.3.dist-info/licenses/NOTICE.txt
raft/IntersectionMesh.py
raft/__init__.py
raft/helpers.py
raft/member2pnl.py
raft/omdao_raft.py
raft/parametersweep.py
raft/pyIECWind.py
raft/raft_fowt.py
raft/raft_member.py
raft/raft_model.py
raft/raft_node.py
raft/raft_rotor.py
raft/runRAFT.py
raft/data/cylinder/Output/ErrorCheck.txt
openraft-2.0.3.dist-info/METADATA
openraft-2.0.3.dist-info/WHEEL
openraft-2.0.3.dist-info/top_level.txt
openraft-2.0.3.dist-info/RECORD
