Metadata-Version: 2.4
Name: OpenRAFT
Version: 2.0.3
Summary: RAFT: Response Amplitudes of Floating Turbines
Author-email: National Renewable Energy Laboratory <matthew.hall@nrel.gov>
Maintainer-email: Matthew Hall <matthew.hall@nrel.gov>, Stein Housner <stein.housner@nrel.gov>, Daniel Zalkind <daniel.zalkind@nrel.gov>, Lucas Carmo <lucas.carmo@nrel.gov>
License: Apache-2.0
Project-URL: Homepage, https://github.com/WISDEM/RAFT
Project-URL: Documentation, https://openraft.readthedocs.io
Keywords: wind,floating,frequency,design,optimization
Classifier: Development Status :: 4 - Beta
Classifier: Intended Audience :: Science/Research
Classifier: Topic :: Scientific/Engineering
Classifier: License :: OSI Approved :: Apache Software License
Classifier: Programming Language :: Python :: 3
Classifier: Programming Language :: Python :: 3.9
Classifier: Programming Language :: Python :: 3.10
Classifier: Programming Language :: Python :: 3.11
Classifier: Programming Language :: Python :: 3.12
Classifier: Programming Language :: Python :: 3.13
Classifier: Programming Language :: Python :: 3.14
Classifier: Programming Language :: Python :: 3 :: Only
Classifier: Operating System :: OS Independent
Requires-Python: >=3.9
License-File: LICENSE
License-File: NOTICE.txt
Requires-Dist: matplotlib
Requires-Dist: moorpy
Requires-Dist: numpy
Requires-Dist: openmdao
Requires-Dist: pyhams
Requires-Dist: pyyaml
Requires-Dist: scipy
Requires-Dist: wisdem
Provides-Extra: dev
Requires-Dist: pre-commit; extra == "dev"
Provides-Extra: docs
Requires-Dist: sphinx; extra == "docs"
Requires-Dist: sphinx-rtd-theme; extra == "docs"
Provides-Extra: test
Requires-Dist: pytest; extra == "test"
Requires-Dist: pytest-cov; extra == "test"
Requires-Dist: pytest-xdist; extra == "test"
Dynamic: license-file
